{"clientes": [{"id": "caa20ad43184d21a512aa2f4f02c1b9e", "name": "KAYLAH", "idade": 48, "credito_solicitado": 221760, "data_solicitacao": "01/03/2022 17:50"}, {"id": "be8208a07a3bb25530ef29c325e7d9e7", "name": "A\u00cdSHO", "idade": 56, "credito_solicitado": 297728, "data_solicitacao": "01/18/2022 16:13"}, {"id": "af9869d7383405b43e540116feaefcba", "name": "ELISSO", "idade": 25, "credito_solicitado": 258107, "data_solicitacao": "01/18/2022 02:18"}, {"id": "914a6c0a3f59d7662fcc98554ec66ea7", "name": "NUIRO", "idade": 33, "credito_solicitado": 319367, "data_solicitacao": "01/13/2022 02:17"}, {"id": "a081e3adac4eb3a9cdb230a2dfda4ab4", "name": "LAKIESHO", "idade": 25, "credito_solicitado": 174869, "data_solicitacao": "01/29/2022 13:26"}]}